testing_packaging_ss/__init__.py
testing_packaging_ss-0.1.dist-info/METADATA
testing_packaging_ss-0.1.dist-info/WHEEL
testing_packaging_ss-0.1.dist-info/top_level.txt
testing_packaging_ss-0.1.dist-info/RECORD
