Metadata-Version: 2.1
Name: testing-packaging-ss
Version: 0.1
Summary: The funniest joke in the world
Home-page: http://github.com/Seemant-tiger/testing_packaging
Author: Seemant Singh
Author-email: seemant.singh@tigeranalytics.com
License: MIT
Platform: UNKNOWN
